tomili/__init__.py
tomili/app.py
tomili/py.typed
tomili-0.1.0.dist-info/METADATA
tomili-0.1.0.dist-info/WHEEL
tomili-0.1.0.dist-info/RECORD
