Metadata-Version: 2.4
Name: tomili
Version: 0.1.0
Summary: ...
Author-email: Antonio Henrique Machado <antoniohenriquemachado08@gmail.com>
Requires-Python: >=3.13
